Beaver-36.3.1.data/scripts/beaver
beaver/__init__.py
beaver/base_log.py
beaver/config.py
beaver/glob_safe_config_parser.py
beaver/pidfile.py
beaver/run_queue.py
beaver/ssh_tunnel.py
beaver/unicode_dammit.py
beaver/utils.py
beaver/dispatcher/__init__.py
beaver/dispatcher/tail.py
beaver/tests/__init__.py
beaver/tests/fixtures.py
beaver/tests/service.py
beaver/tests/test_glob_sections.py
beaver/tests/test_kafka_transport.py
beaver/tests/test_kinesis_transport.py
beaver/tests/test_sqs_transport.py
beaver/tests/test_transport_config.py
beaver/tests/test_zmq_transport.py
beaver/transports/__init__.py
beaver/transports/base_transport.py
beaver/transports/exception.py
beaver/transports/http_transport.py
beaver/transports/kafka_transport.py
beaver/transports/kinesis_transport.py
beaver/transports/mqtt_transport.py
beaver/transports/rabbitmq_transport.py
beaver/transports/redis_transport.py
beaver/transports/sns_transport.py
beaver/transports/sqs_transport.py
beaver/transports/stdout_transport.py
beaver/transports/stomp_transport.py
beaver/transports/tcp_transport.py
beaver/transports/udp_transport.py
beaver/transports/zmq_transport.py
beaver/worker/__init__.py
beaver/worker/tail.py
beaver/worker/tail_manager.py
Beaver-36.3.1.dist-info/LICENSE.txt
Beaver-36.3.1.dist-info/METADATA
Beaver-36.3.1.dist-info/WHEEL
Beaver-36.3.1.dist-info/pbr.json
Beaver-36.3.1.dist-info/top_level.txt
Beaver-36.3.1.dist-info/RECORD
