Metadata-Version: 2.1
Name: Beaver
Version: 36.3.1
Summary: python daemon that munches on logs and sends their contents to logstash
Home-page: http://github.com/python-beaver/python-beaver
Author: Jose Diaz-Gonzalez
Author-email: email@josediazgonzalez.com
License: LICENSE.txt
Platform: UNKNOWN
Classifier: Development Status :: 5 - Production/Stable
Classifier: Intended Audience :: System Administrators
Classifier: License :: OSI Approved :: MIT License
Classifier: Programming Language :: Python :: 2.6
Classifier: Programming Language :: Python :: 2.7
Classifier: Topic :: System :: Logging
Requires: six
Requires-Dist: boto (>=2.18.0)
Requires-Dist: conf-d (>=0.0.4)
Requires-Dist: glob2 (==0.3)
Requires-Dist: kafka-python (==0.9.5)
Requires-Dist: paho-mqtt (==1.1)
Requires-Dist: msgpack-pure (>=0.1.3)
Requires-Dist: pika (<1.0.0,>=0.9.14)
Requires-Dist: python-daemon (<=1.6.1,>=1.5.2)
Requires-Dist: redis (>=2.7.5)
Requires-Dist: requests
